newberry_metrics/__init__.py
newberry_metrics/_version.py
newberry_metrics/app.py
newberry_metrics/bedrock_models.py
newberry_metrics/main.py
newberry_metrics-0.2.1.dist-info/licenses/LICENSE
newberry_metrics-0.2.1.dist-info/METADATA
newberry_metrics-0.2.1.dist-info/WHEEL
newberry_metrics-0.2.1.dist-info/top_level.txt
newberry_metrics-0.2.1.dist-info/RECORD
