Metadata-Version: 2.4
Name: newberry_metrics
Version: 0.2.1
Summary: A Python package for tracking Bedrock API usage metrics (cost, latency, tokens) with an automatically launched dashboard
Home-page: https://github.com/Satya-Holbox/newberry_metrics/
Author: Harshika Agarwal,Satyanarayan Sahoo
Author-email: harshika@holbox.ai,satyanarayan@holbox.ai
License: MIT
Classifier: License :: OSI Approved :: MIT License
Classifier: Programming Language :: Python :: 3.10
Classifier: Operating System :: OS Independent
Requires-Python: >=3.10
License-File: LICENSE
Requires-Dist: pytest
Requires-Dist: setuptools
Requires-Dist: wheel
Requires-Dist: setuptools_scm[toml]
Requires-Dist: boto3
Requires-Dist: matplotlib
Requires-Dist: pandas
Requires-Dist: streamlit
Requires-Dist: plotly
Dynamic: author
Dynamic: author-email
Dynamic: classifier
Dynamic: description
Dynamic: description-content-type
Dynamic: home-page
Dynamic: license
Dynamic: license-file
Dynamic: requires-dist
Dynamic: requires-python
Dynamic: summary
